helmYAMLizer.py
tests/__init__.py
tests/test_drop_label_keys.py
tests/test_ensure_dirs_exists.py
tests/test_flatten_source_path.py
tests/test_get_first_line_comment.py
tests/test_get_template_source_path.py
tests/test_kustomize.py
tests/test_prepare_file_path.py
tests/test_save_document_to_file.py
tests/utils.py
helmYAMLizer-1.0.8.dist-info/LICENSE
helmYAMLizer-1.0.8.dist-info/METADATA
helmYAMLizer-1.0.8.dist-info/WHEEL
helmYAMLizer-1.0.8.dist-info/entry_points.txt
helmYAMLizer-1.0.8.dist-info/top_level.txt
helmYAMLizer-1.0.8.dist-info/RECORD
