Metadata-Version: 2.1
Name: helmYAMLizer
Version: 1.0.8
Summary: Minimal local renderer for Helm template YAML
Author: VioletCranberry
Project-URL: Homepage, https://github.com/VioletCranberry/helmYAMLizer
Classifier: Programming Language :: Python :: 3
Classifier: License :: OSI Approved :: Apache Software License
Classifier: Operating System :: OS Independent
Requires-Python: >=3.7
License-File: LICENSE
Requires-Dist: ruamel.yaml ==0.18.6
Requires-Dist: ruamel.yaml.clib ==0.2.12
